estimate_pi/__init__.py
estimate_pi/estimate_pi.py
estimate_pi/plot_tools.py
estimate_pi-0.2.0.dist-info/WHEEL
estimate_pi-0.2.0.dist-info/METADATA
estimate_pi-0.2.0.dist-info/RECORD
