Metadata-Version: 2.1
Name: estimate-pi
Version: 0.2.0
Summary: 
Author: Chang-Goo Kim
Author-email: changgoo@princeton.edu
Requires-Python: >=3.8,<4.0
Classifier: Programming Language :: Python :: 3
Classifier: Programming Language :: Python :: 3.10
Classifier: Programming Language :: Python :: 3.8
Classifier: Programming Language :: Python :: 3.9
Requires-Dist: matplotlib (>=3.5.2,<4.0.0)
Requires-Dist: numpy (>=1.22.4,<2.0.0)
